nameko_pony/__init__.py
nameko_pony-1.3.1.dist-info/METADATA
nameko_pony-1.3.1.dist-info/RECORD
nameko_pony-1.3.1.dist-info/WHEEL
nameko_pony-1.3.1.dist-info/top_level.txt
